easiersnmp/__init__.py
easiersnmp-0.2.0.dist-info/LICENSE
easiersnmp-0.2.0.dist-info/METADATA
easiersnmp-0.2.0.dist-info/WHEEL
easiersnmp-0.2.0.dist-info/RECORD
