Metadata-Version: 2.1
Name: easiersnmp
Version: 0.2.0
Summary: easiersnmp is a wrapper around easysnmp to make it even easier to use
License: BSD 2-Clause License
Author: Markus Juenemann
Author-email: markus@juenemann.net
Requires-Python: >=3.7,<4.0
Classifier: License :: Other/Proprietary License
Classifier: Programming Language :: Python :: 3
Classifier: Programming Language :: Python :: 3.7
Classifier: Programming Language :: Python :: 3.8
Classifier: Programming Language :: Python :: 3.9
Classifier: Programming Language :: Python :: 3.10
Classifier: Programming Language :: Python :: 3.11
Classifier: Programming Language :: Python :: 3.12
Requires-Dist: easysnmp (>=0.2.6,<0.3.0)
